{"data":{"issuanceinfo":{"industrycode":"208004","industry":"其他金融","ipoprice":{"ceiling":"2.280","floor":"1.880"},"ipodate":{"start":"2013-10-16 00:00:00","end":"2013-10-21 00:00:00"},"minimumcapital":"4605.96","subscribed":"243.10","marketcap":"22.35億","H_marketcap":"--","pe":"0.14","codesrate":"100.00","link":"https://staticpdf.iqdii.com/stockdata/notice/Prospectus/01290/LTN20131016024_C.pdf","ipopricing":"2.180","resultdate":"2013-10-25 00:00:00","enddate":"2013-10-21 00:00:00","listeddate":"2013-10-28 00:00:00","issuenumber":"37523.60萬","issuenumberhK":"3752.40萬","issuenumberother":"33771.20萬","grayprice":"--","sponsors":"瑞銀證券香港有限公司","raisemoney":"73160.00萬","use":"1、約90%或65850萬港幣將用于向中國經營實體注入注冊資本以供短期短期抵押融資服務之用； 2、約10%所得款項凈額將用于本公司的營運資金及其他一般企業用途提供資金。","shares":2000,"leadagent":"瑞士銀行香港分行","bookrunners":"瑞士銀行香港分行","coordinator":"瑞士銀行香港分行","firstDayOpen":"2.18","IsEiio":0,"Interestdays":4,"PENote":"按經審核的最近年度公司股東應占溢利和發行后總股本計算；發行價未確定時，按招股價中間價計算；發行價確定后，按招股定價計算。","OverAllotment":"有","StabilizingManager":"--","code":"E01290","name":"中國匯融","fullname":"中國匯融金融控股有限公司"},"institutioninfo":{"principaloffice":"中國江蘇省蘇州市寶帶東路345號22樓","registrars":"香港中央證券登記有限公司","registrarstel":"(852) 2862 8628","chairman":"吳敏","secretary":"梁晶晶,柴琨","telephone":"(0512) 6605 1290","substantialshareholders":"朱天曉(29.92%),張祥榮(7.78%),葛健(6.58%),陳雁南(5.98%)","principalactivities":"在中國提供短期抵押融資服務。","website":"http://www.cnhuirong.com"},"managerinfo":[],"investorinfo":[],"TotalShareholdingPercentage":0},"result":1,"Version":"4.5.190802.46408","ElapsedMilliseconds":507}