{"data":{"issuanceinfo":{"industrycode":"209002","industry":"建筑","ipoprice":{"ceiling":"0.140","floor":"0.120"},"ipodate":{"start":"2016-09-12 00:00:00","end":"2016-09-15 00:00:00"},"minimumcapital":"2828.00","subscribed":"382.00","marketcap":"5.20億","H_marketcap":"--","pe":"20.31","codesrate":"1.61","link":"https://staticpdf.iqdii.com/stockdata/notice/Prospectus/01591/LTN20160912006_C.pdf","ipopricing":"0.130","resultdate":"2016-09-27 00:00:00","enddate":"2016-09-15 00:00:00","listeddate":"2016-09-28 00:00:00","issuenumber":"100000.00萬","issuenumberhK":"50000.00萬","issuenumberother":"50000.00萬","grayprice":"0.15","sponsors":"德健融資有限公司","raisemoney":"8420.00萬","use":"1、約55.0百萬港元（所得款項凈額約65.3%）將用于增加機械，在未來3年購置更多挖掘機、起重機及液壓破碎機；\n2、約15.0百萬港元（所得款項凈額約17.8%）將用于加強人手，在未來3年招聘更多員工，包括項目管理及執行員工以及人力資源、行政及會計員工；\n3、約6.2百萬港元（所得款項凈額約7.4%）將用于在未來4年額外增加營銷力度，擴大公司宣傳；\n4、約8.0百萬港元（所得款項凈額約9.5%）將用作一般營運資金。","shares":20000,"leadagent":"德健證券有限公司,聯合證券有限公司","bookrunners":"聯合證券有限公司","coordinator":"","firstDayOpen":"0.15","IsEiio":0,"Interestdays":12,"PENote":"按經審核的最近年度公司股東應占溢利和發行后總股本計算；發行價未確定時，按招股價中間價計算；發行價確定后，按招股定價計算。","OverAllotment":"有","StabilizingManager":"聯合證券有限公司","code":"E01591","name":"汛和集團","fullname":"汛和集團控股有限公司"},"institutioninfo":{"principaloffice":"香港筲箕灣道68號西灣河中心7樓A室","registrars":"寶德隆證券登記有限公司","registrarstel":"(852) 2598 5234","chairman":"黃仁雄","secretary":"徐永裕","telephone":"(852) 2568 9611","substantialshareholders":"黃仁雄及關連人士(51.00%)","principalactivities":"公司是香港的地基工程承包商，主要包括挖掘及側向承托工程、嵌巖工字樁及迷你樁工程以及樁帽建設工程，主要服務于住宅、工業及商業樓宇建設。","website":"http://www.shunwogroup.com"},"managerinfo":[{"managername":"黃仁雄","post":"董事會主席兼執行董事","rankno":1},{"managername":"黃義邦","post":"執行董事兼行政總裁","rankno":2},{"managername":"黎國輝","post":"執行董事兼營運總監","rankno":3}],"investorinfo":[],"TotalShareholdingPercentage":0},"result":1,"Version":"4.5.190802.46408","ElapsedMilliseconds":525}