{"data":{"issuanceinfo":{"industrycode":"204001","industry":"汽車","ipoprice":{"ceiling":"0.470","floor":"0.430"},"ipodate":{"start":"2019-02-13 00:00:00","end":"2019-02-18 00:00:00"},"minimumcapital":"2373.68","subscribed":"72.47","marketcap":"3.87億","H_marketcap":"--","pe":"9.19","codesrate":"50.01","link":"https://staticpdf.iqdii.com/stockdata/notice/Prospectus/01872/LTN20190213014_C.pdf","ipopricing":"0.430","resultdate":"2019-02-27 00:00:00","enddate":"2019-02-18 00:00:00","listeddate":"2019-02-28 00:00:00","issuenumber":"22500.00萬","issuenumberhK":"9000.00萬","issuenumberother":"13500.00萬","grayprice":"0.51","sponsors":"天泰金融服務有限公司","raisemoney":"5650.00萬","use":"1、所得款項的45.8%或約25.9百萬港元，將用于擴大我們的汽車租購 融資業務的規模；\n2、所得款項的30.2%或約17.1百萬港元，將用于擴大我們的二手車銷售業務的規模；\n3、所得款項的10.4%或約5.9百萬港元，將用于建立一個汽車車間；\n4、所得款項的7.7%或約4.3百萬港元，將用于加強品牌、銷售及市場推廣工作；\n5、所得款項的5.9%或約3.3百萬港元，將用于一般營運資金。","shares":5000,"leadagent":"天泰金融服務有限公司,鴻鵬資本證券有限公司","bookrunners":"天泰金融服務有限公司,鴻鵬資本證券有限公司","coordinator":"","firstDayOpen":"0.49","IsEiio":0,"Interestdays":9,"PENote":"按經審核的最近年度公司股東應占溢利和發行后總股本計算；發行價未確定時，按招股價中間價計算；發行價確定后，按招股定價計算。","OverAllotment":"--","StabilizingManager":"--","code":"E01872","name":"冠轈控股","fullname":"冠轈控股有限公司"},"institutioninfo":{"principaloffice":"1 Chang Charn Road #05-02,OC Building Singapore","registrars":"卓佳證券登記有限公司","registrarstel":"(852)2980 1333","chairman":"陳率堂","secretary":"呂偉勝","telephone":"(65)6590 9973","substantialshareholders":"Gatehouse Ventures(67.3%)","principalactivities":"公司是位于新加坡的汽車集團，銷售新平行進口汽車及二手車，于業績記錄期，主要業務為銷售全新平行進口汽車。","website":"www.guanchaoholdingsltd.com"},"managerinfo":[{"managername":"陳率堂","post":"主席、行政總裁兼執行董事","rankno":1},{"managername":"黃慧敏","post":"行政及運營部高級經理兼執行董事","rankno":2},{"managername":"康寶山","post":"運營及物流部總監兼執行董事","rankno":3}],"investorinfo":[],"TotalShareholdingPercentage":0},"result":1,"Version":"4.5.190802.46408","ElapsedMilliseconds":512}