{"data":{"issuanceinfo":{"industrycode":"205003","industry":"影視傳媒","ipoprice":{"ceiling":"6.160","floor":"5.100"},"ipodate":{"start":"2020-12-31 00:00:00","end":"2021-01-08 00:00:00"},"minimumcapital":"6222.08","subscribed":"403.54","marketcap":"38.99億","H_marketcap":"--","pe":"70.00","codesrate":"6.00","link":"https://staticpdf.iqdii.com/stockdata/notice/02125/2020/2020123100264_c.pdf","ipopricing":"5.880","resultdate":"2021-01-14 00:00:00","enddate":"2021-01-08 00:00:00","listeddate":"2021-01-15 00:00:00","issuenumber":"16578.00萬","issuenumberhK":"8289.00萬","issuenumberother":"8289.00萬","grayprice":"8.00","sponsors":"招商證券(香港)有限公司,中信建投(國際)融資有限公司","raisemoney":"92780.00萬","use":"1、約70%或649.5百萬港元將用于撥付本公司的劇集制作；\n2、約10%或92.8百萬港元將用于撥付對可提高本公司市場地位及加快我們劇集開發、制作及發行的公司進行的潛在投資或并購；\n3、約10%或92.8百萬港元將用于取得更多IP以透過收購一家專注于網劇投資、開發、制作及發行的優質版權公司，確保劇集制作及發行穩定增長；\n4、約10%或92.8百萬港元將用作營運資金及一般企業用途。","shares":1000,"leadagent":"招商證券(香港)有限公司,中信建投(國際)融資有限公司，華興證券(香港)有限公司,農銀國際證券有限公司,海通國際證券有限公司,交銀國際證券有限公司,華泰金融控股(香港)有限公司,招銀國際融資有限公司,富途證券國際(香港)有限公司,中國銀河國際證券(香港)有限公司","bookrunners":"招商證券(香港)有限公司,中信建投(國際)融資有限公司，華興證券(香港)有限公司,農銀國際融資有限公司,海通國際證券有限公司,交銀國際證券有限公司,華泰金融控股(香港)有限公司,招銀國際融資有限公司,富途證券國際(香港)有限公司","coordinator":"招商證券(香港)有限公司,中信建投(國際)融資有限公司，華興證券(香港)有限公司","firstDayOpen":"7.00","IsEiio":0,"Interestdays":6,"PENote":"按經審核的最近年度公司股東應占溢利和發行后總股本計算；發行價未確定時，按招股價中間價計算；發行價確定后，按招股定價計算。","OverAllotment":"有","StabilizingManager":"中信建投(國際)融資有限公司","code":"E02125","name":"稻草熊娛樂","fullname":"稻草熊娛樂集團"},"institutioninfo":{"principaloffice":"中國江蘇省南京市建鄴區江東中路98號萬達廣場A座2508室","registrars":"卓佳證券登記有限公司","registrarstel":"(852) 2980 1333","chairman":"劉小楓","secretary":"翟芳,王承鏱","telephone":"(8625) 5805 551","substantialshareholders":"Leading Glory(43.81%),Taurus Holding(14.68%),Glesason Global(11.1%)","principalactivities":"公司為中國主要的劇集制片商及發行商，涵蓋電視劇及網劇的投資、開發、制作及發行。","website":"http://www.strawbearentertainment.com"},"managerinfo":[{"managername":"劉小楓","post":"主席、行政總裁兼執行董事","rankno":1},{"managername":"張秋晨","post":"執行董事","rankno":2},{"managername":"陳晨","post":"執行董事","rankno":3}],"investorinfo":[{"institutionname":"Snow Lake China Master Fund, Ltd.","shareholding":"46,309,000.0","percentage":27.9,"ReleaseDate":"2021-07-15 00:00:00","relatedparty":"雪湖資本(香港)有限公司","subsidiary":["Snow Lake China Master Fund, Ltd."],"InverstorType":"基金"},{"institutionname":"Origin Flair Limited","shareholding":"13,231,000.0","percentage":8,"ReleaseDate":"2021-07-15 00:00:00","relatedparty":"Nimble Express Limited","subsidiary":["Origin Flair Limited"],"InverstorType":"公司"},{"institutionname":"Vipshop International Holdings Limited","shareholding":"6,615,000.0","percentage":4,"ReleaseDate":"2021-07-15 00:00:00","relatedparty":"Vipshop Holdings Limited","subsidiary":["Vipshop International Holdings Limited"],"InverstorType":"公司"}],"TotalShareholdingPercentage":39.9},"result":1,"Version":"4.5.190802.46408","ElapsedMilliseconds":9}