{"data":{"issuanceinfo":{"industrycode":"205005","industry":"居民服務","ipoprice":{"ceiling":"1.100","floor":"1.000"},"ipodate":{"start":"2018-11-29 00:00:00","end":"2018-12-04 00:00:00"},"minimumcapital":"2222.17","subscribed":"59.44","marketcap":"5.00億","H_marketcap":"--","pe":"14.20","codesrate":"30.00","link":"https://staticpdf.iqdii.com/stockdata/notice/Prospectus/03992/LTN20181129020_C.pdf","ipopricing":"1.000","resultdate":"2018-12-10 00:00:00","enddate":"2018-12-04 00:00:00","listeddate":"2018-12-11 00:00:00","issuenumber":"12500.00萬","issuenumberhK":"5000.00萬","issuenumberother":"7500.00萬","grayprice":"0.81","sponsors":"第一上海融資有限公司","raisemoney":"9940.00萬","use":"1、約71.5百萬港元（約72.0%）將用作營運資金及現金存款獲得履約保證以承接公共及私人客戶的額外物業管理服務合約、獨立護衛服務合約及獨立潔凈服務合約；\n2、約4.7百萬港元（約4.7%）將用于升級計算機系統及會計系統；\n3、約18.9百萬港元（約19.0%）將用于于香港收購物業管理公司；\n4、約4.3百萬港元（約4.3%）將用作本集團一般營運資金。","shares":2000,"leadagent":"第一上海證券有限公司,海通國際證券有限公司","bookrunners":"第一上海證券有限公司,海通國際證券有限公司","coordinator":"","firstDayOpen":"0.77","IsEiio":0,"Interestdays":6,"PENote":"按經審核的最近年度公司股東應占溢利和發行后總股本計算；發行價未確定時，按招股價中間價計算；發行價確定后，按招股定價計算。","OverAllotment":"有","StabilizingManager":"第一上海證券有限公司","code":"E03992","name":"創毅控股","fullname":"創毅控股有限公司"},"institutioninfo":{"principaloffice":"香港新界葵涌打磚坪街49–53號華基工業大廈2座25樓E及F室","registrars":"卓佳證券登記有限公司","registrarstel":"(852)2980 1333","chairman":"潘建良","secretary":"梁文輝","telephone":"(852)2666 5340","substantialshareholders":"Genesis Group Limited(53.51%),蘇爾雅(6.56%)","principalactivities":"公司是香港公共房屋的領先物業管理服務供應商。","website":"http://www.cpsc.hk"},"managerinfo":[{"managername":"潘建良","post":"主席兼執行董事","rankno":1},{"managername":"李兆華","post":"行政總裁兼執行董事","rankno":2},{"managername":"林少鴻","post":"執行董事","rankno":3}],"investorinfo":[],"TotalShareholdingPercentage":0},"result":1,"Version":"4.5.190802.46408","ElapsedMilliseconds":517}